conflare/__init__.py
conflare/main.py
conflare/augmented_retrieval/__init__.py
conflare/augmented_retrieval/embed.py
conflare/augmented_retrieval/rag.py
conflare/augmented_retrieval/vector_db.py
conflare/conformal/__init__.py
conflare/conformal/calibration.py
conflare/models/__init__.py
conflare/models/hf.py
conflare/models/openai.py
conflare/utils/__init__.py
conflare/utils/loaders.py
conflare/utils/preprocess.py
conflare/utils/prompts.py
conflare-0.1.3.dist-info/LICENSE
conflare-0.1.3.dist-info/METADATA
conflare-0.1.3.dist-info/WHEEL
conflare-0.1.3.dist-info/top_level.txt
conflare-0.1.3.dist-info/RECORD
