Metadata-Version: 2.1
Name: conflare
Version: 0.1.3
Summary: conformal retreival augmented generation with LLMs
Home-page: https://github.com/Mayo-Radiology-Informatics-Lab/conflare
Author: Moein Shariatnia
Author-email: moein.shariatnia@gmail.com
License: MIT
Classifier: License :: OSI Approved :: MIT License
Classifier: Programming Language :: Python :: 3.10
Classifier: Operating System :: OS Independent
Requires-Python: >=3.10
License-File: LICENSE
Requires-Dist: pypdf ==4.1.0
Requires-Dist: torch >=2.0.0
Requires-Dist: transformers ==4.37.2
Requires-Dist: bitsandbytes ==0.42.0
Requires-Dist: accelerate ==0.26.1
Requires-Dist: openai ==1.12.0
Requires-Dist: sentence-transformers ==2.3.1
Requires-Dist: chromadb ==0.4.22
